{
  "id": "2958619",
  "name": "vue-shop",
  "font_family": "iconfont",
  "css_prefix_text": "icon-",
  "description": "",
  "glyphs": [
    {
      "icon_id": "6446244",
      "name": "密码（关）",
      "font_class": "lock",
      "unicode": "e638",
      "unicode_decimal": 58936
    },
    {
      "icon_id": "9712650",
      "name": "用户",
      "font_class": "username",
      "unicode": "e6b2",
      "unicode_decimal": 59058
    },
    {
      "icon_id": "8776631",
      "name": "view",
      "font_class": "icon-test",
      "unicode": "e633",
      "unicode_decimal": 58931
    },
    {
      "icon_id": "8776676",
      "name": "view_off",
      "font_class": "icon-test1",
      "unicode": "e634",
      "unicode_decimal": 58932
    }
  ]
}
